geo_country_service/__init__.py
geo_country_service/handler.py
geo_country_service/world_countries.geojson
geo_country_service-0.5.0.dist-info/LICENSE
geo_country_service-0.5.0.dist-info/METADATA
geo_country_service-0.5.0.dist-info/WHEEL
geo_country_service-0.5.0.dist-info/RECORD
