Metadata-Version: 2.3
Name: geo-country-service
Version: 0.5.0
Summary: A service that provides an alpha-3 country code from given coordinates
Author: Benas Jasikonis
Author-email: benasjasikonis@carvertical.com
Requires-Python: >=3.11
Classifier: Programming Language :: Python :: 3
Classifier: Programming Language :: Python :: 3.11
Classifier: Programming Language :: Python :: 3.12
Classifier: Programming Language :: Python :: 3.13
Requires-Dist: orjson (==3.10)
Requires-Dist: pytest (==8.4.0)
Requires-Dist: shapely (==2.1.0)
